mdm_compare.py
mdm_compare-1.0.6.dist-info/AUTHORS
mdm_compare-1.0.6.dist-info/LICENSE
mdm_compare-1.0.6.dist-info/METADATA
mdm_compare-1.0.6.dist-info/WHEEL
mdm_compare-1.0.6.dist-info/entry_points.txt
mdm_compare-1.0.6.dist-info/top_level.txt
mdm_compare-1.0.6.dist-info/RECORD
