Metadata-Version: 2.1
Name: mdm-compare
Version: 1.0.6
Summary: Console app and Python API for comparing 2 experiment results stored in the MDM file format.
Home-page: https://github.com/petarmaric/mdm_compare
Author: Petar Maric
Author-email: petarmaric@uns.ac.rs
License: BSD
Download-URL: https://github.com/petarmaric/mdm_compare
Platform: any
Classifier: Development Status :: 5 - Production/Stable
Classifier: Environment :: Console
Classifier: Intended Audience :: Developers
Classifier: Intended Audience :: Science/Research
Classifier: License :: OSI Approved :: BSD License
Classifier: Operating System :: OS Independent
Classifier: Programming Language :: Python
Classifier: Programming Language :: Python :: 2.6
Classifier: Topic :: Scientific/Engineering
Classifier: Topic :: Scientific/Engineering :: Physics
Requires-Dist: numpy (>=1.3)
Requires-Dist: nose (>=1.0)
Requires-Dist: coverage (>=3.3)
Requires-Dist: nosexcover (>=1.0.7)
